risk_distributions/__about__.py
risk_distributions/__init__.py
risk_distributions/_version.py
risk_distributions/formatting.py
risk_distributions/risk_distributions.py
risk_distributions-2.2.2.dist-info/licenses/AUTHORS.rst
risk_distributions-2.2.2.dist-info/licenses/LICENSE.txt
risk_distributions-2.2.2.dist-info/METADATA
risk_distributions-2.2.2.dist-info/WHEEL
risk_distributions-2.2.2.dist-info/top_level.txt
risk_distributions-2.2.2.dist-info/RECORD
