Metadata-Version: 2.4
Name: risk_distributions
Version: 2.2.2
Summary: Components for building distributions. Compatible for use with ``vivarium``
Home-page: https://github.com/ihmeuw/risk_distributions
Author: The risk_distributions developers
Author-email: vivarium.dev@gmail.com
License: BSD-3-Clause
Classifier: Intended Audience :: Developers
Classifier: Intended Audience :: Science/Research
Classifier: License :: OSI Approved :: GNU General Public License v3 or later (GPLv3+)
Classifier: Natural Language :: English
Classifier: Operating System :: MacOS :: MacOS X
Classifier: Operating System :: POSIX
Classifier: Operating System :: POSIX :: BSD
Classifier: Operating System :: POSIX :: Linux
Classifier: Operating System :: Microsoft :: Windows
Classifier: Programming Language :: Python
Classifier: Programming Language :: Python :: Implementation :: CPython
Classifier: Topic :: Education
Classifier: Topic :: Scientific/Engineering
Classifier: Topic :: Software Development :: Libraries
License-File: LICENSE.txt
License-File: AUTHORS.rst
Requires-Dist: vivarium_dependencies[numpy,pandas,scipy]
Requires-Dist: vivarium_build_utils<3.0.0,>=2.0.1
Provides-Extra: test
Requires-Dist: vivarium_dependencies[pytest]; extra == "test"
Provides-Extra: docs
Requires-Dist: vivarium_dependencies[sphinx]; extra == "docs"
Provides-Extra: interactive
Requires-Dist: vivarium_dependencies[interactive]; extra == "interactive"
Provides-Extra: dev
Requires-Dist: vivarium_dependencies[pytest]; extra == "dev"
Requires-Dist: vivarium_dependencies[sphinx]; extra == "dev"
Requires-Dist: vivarium_dependencies[interactive]; extra == "dev"
Requires-Dist: vivarium_dependencies[lint]; extra == "dev"
Dynamic: author
Dynamic: author-email
Dynamic: classifier
Dynamic: description
Dynamic: home-page
Dynamic: license
Dynamic: license-file
Dynamic: provides-extra
Dynamic: requires-dist
Dynamic: summary
